LICENSE
README.md
setup.cfg
setup.py
pyllm/__init__.py
pyllm/exceptions.py
pyllm/llm.py
pyllm/types.py
pyllm/clients/__init__.py
pyllm/clients/client.py
pyllm/clients/openai_client.py
pyllm/parsers/__init__.py
pyllm/parsers/parser.py
pyllm/parsers/regex_parser.py
pyllm/templates/__init__.py
pyllm/templates/template.py
pyllm/templates/jinja/__init__.py
pyllm_code.egg-info/PKG-INFO
pyllm_code.egg-info/SOURCES.txt
pyllm_code.egg-info/dependency_links.txt
pyllm_code.egg-info/requires.txt
pyllm_code.egg-info/top_level.txt
tests/__init__.py
tests/test_llm.py