Metadata-Version: 2.1
Name: pyllm-code
Version: 0.0.2
Summary: Leverage LLMs to generate and execute robust code dynamically through an intuitive and easy-to-use API!
Home-page: https://github.com/HishamYahya/PyLLM
Download-URL: https://github.com/HishamYahya/PyLLM/archive/refs/tags/v0.0.2.tar.gz
Author: Hisham Alyahya
Author-email: Hishamaalyahya@gmail.com
License: MIT
Keywords: LLM,LLMs,assistant,helper,coding,automation,AI,NLP
Classifier: Development Status :: 3 - Alpha
Classifier: Intended Audience :: Developers
Classifier: Topic :: Software Development :: Build Tools
Classifier: Topic :: Scientific/Engineering :: Artificial Intelligence
Classifier: License :: OSI Approved :: MIT License
Classifier: Programming Language :: Python :: 3.7
Classifier: Programming Language :: Python :: 3.8
Classifier: Programming Language :: Python :: 3.9
Classifier: Programming Language :: Python :: 3.10
Classifier: Programming Language :: Python :: 3.11
License-File: LICENSE
Requires-Dist: filelock
Requires-Dist: Jinja2
Requires-Dist: Requests
Requires-Dist: appdirs
Requires-Dist: pytest
